electroid/__init__.py
electroid/roid.py
electroid-0.0.3.dist-info/licenses/LICENSE
electroid-0.0.3.dist-info/METADATA
electroid-0.0.3.dist-info/WHEEL
electroid-0.0.3.dist-info/top_level.txt
electroid-0.0.3.dist-info/RECORD
